README.md
setup.py
captor/__init__.py
captor/captor.py
captor.egg-info/PKG-INFO
captor.egg-info/SOURCES.txt
captor.egg-info/dependency_links.txt
captor.egg-info/entry_points.txt
captor.egg-info/requires.txt
captor.egg-info/top_level.txt