Metadata-Version: 2.1
Name: captor
Version: 0.0.1
Summary: 用于捕获接口并转换为可导入metersphere平台的json格式
Home-page: https://github.com/zerobyte1o1/captureTraffic
Author: byte
Author-email: liufangjing_byte@163.com
Classifier: Programming Language :: Python :: 3
Classifier: License :: OSI Approved :: MIT License
Classifier: Operating System :: OS Independent
Requires-Python: >=3
